flagquantum/__init__.py
flagquantum-0.1.1.dist-info/METADATA
flagquantum-0.1.1.dist-info/WHEEL
flagquantum-0.1.1.dist-info/top_level.txt
flagquantum-0.1.1.dist-info/RECORD
