Metadata-Version: 2.4
Name: flagquantum
Version: 0.1.1
Summary: Distributed Quantum-Classical Hybrid AI System Framework
Author-email: Wei Liu <liuwei.chem.phys@gmail.com>
License: Apache-2.0
Project-URL: Homepage, https://github.com/FlagQuantum/flagquantum
Classifier: Programming Language :: Python :: 3
Classifier: License :: OSI Approved :: Apache Software License
Classifier: Operating System :: OS Independent
Requires-Python: >=3.7
